./.gitignore
./PKG-INFO
./README.md
./pyproject.toml
./mp_scrape_cli/__init__.py
./mp_scrape_cli/__main__.py
./mp_scrape_cli/examples/parliaments.toml
mp_scrape_cli-0.1.8.dist-info/METADATA
mp_scrape_cli-0.1.8.dist-info/WHEEL
mp_scrape_cli-0.1.8.dist-info/RECORD
